README.md
setup.cfg
setup.py
ombt/__init__.py
ombt/_main.py
ombt.egg-info/PKG-INFO
ombt.egg-info/SOURCES.txt
ombt.egg-info/dependency_links.txt
ombt.egg-info/entry_points.txt
ombt.egg-info/requires.txt
ombt.egg-info/top_level.txt