Metadata-Version: 2.1
Name: ombt
Version: 3.0.0
Summary: Oslo.Messaging Benchmark Tool
Home-page: https://github.com/kgiusti/ombt
Author: Ken Giusti
Author-email: kgiusti@gmail.com
License: Apache Software License
Platform: UNKNOWN
Classifier: License :: OSI Approved :: Apache Software License
Classifier: Intended Audience :: Developers
Classifier: Operating System :: OS Independent
Classifier: Programming Language :: Python
Classifier: Programming Language :: Python :: 2
Classifier: Programming Language :: Python :: 2.7
Classifier: Programming Language :: Python :: 3
Classifier: Programming Language :: Python :: 3.3
Classifier: Programming Language :: Python :: 3.4
Classifier: Programming Language :: Python :: 3.5
Classifier: Programming Language :: Python :: 3.6
Provides-Extra: amqp1
Provides-Extra: kafka
